{"copyright":"NHL and the NHL Shield are registered trademarks of the National Hockey League. NHL and NHL team marks are the property of the NHL and its teams. © NHL 2022. All Rights Reserved.","gamePk":2022021006,"link":"/api/v1/game/2022021006/feed/live","metaData":{"wait":10,"timeStamp":"20220907_224930"},"gameData":{"game":{"pk":2022021006,"season":"20222023","type":"R"},"datetime":{"dateTime":"2023-03-07T00:30:00Z"},"status":{"abstractGameState":"Preview","codedGameState":"1","detailedState":"Scheduled","statusCode":"1","startTimeTBD":false},"teams":{"away":{"id":22,"name":"Edmonton Oilers","link":"/api/v1/teams/22","venue":{"id":5100,"name":"Rogers Place","link":"/api/v1/venues/5100","city":"Edmonton","timeZone":{"id":"America/Edmonton","offset":-6,"tz":"MDT"}},"abbreviation":"EDM","triCode":"EDM","teamName":"Oilers","locationName":"Edmonton","firstYearOfPlay":"1979","division":{"id":15,"name":"Pacific","nameShort":"PAC","link":"/api/v1/divisions/15","abbreviation":"P"},"conference":{"id":5,"name":"Western","link":"/api/v1/conferences/5"},"franchise":{"franchiseId":25,"teamName":"Oilers","link":"/api/v1/franchises/25"},"shortName":"Edmonton","officialSiteUrl":"http://www.edmontonoilers.com/","franchiseId":25,"active":true},"home":{"id":7,"name":"Buffalo Sabres","link":"/api/v1/teams/7","venue":{"id":5039,"name":"KeyBank Center","link":"/api/v1/venues/5039","city":"Buffalo","timeZone":{"id":"America/New_York","offset":-4,"tz":"EDT"}},"abbreviation":"BUF","triCode":"BUF","teamName":"Sabres","locationName":"Buffalo","firstYearOfPlay":"1970","division":{"id":17,"name":"Atlantic","nameShort":"ATL","link":"/api/v1/divisions/17","abbreviation":"A"},"conference":{"id":6,"name":"Eastern","link":"/api/v1/conferences/6"},"franchise":{"franchiseId":19,"teamName":"Sabres","link":"/api/v1/franchises/19"},"shortName":"Buffalo","officialSiteUrl":"http://www.sabres.com/","franchiseId":19,"active":true}},"players":{},"venue":{"id":5039,"name":"KeyBank Center","link":"/api/v1/venues/5039"}},"liveData":{"plays":{"allPlays":[],"scoringPlays":[],"penaltyPlays":[],"playsByPeriod":[]},"linescore":{"currentPeriod":0,"periods":[],"shootoutInfo":{"away":{"scores":0,"attempts":0},"home":{"scores":0,"attempts":0}},"teams":{"home":{"team":{"id":7,"name":"Buffalo Sabres","link":"/api/v1/teams/7","abbreviation":"BUF","triCode":"BUF"},"goals":0,"shotsOnGoal":0,"goaliePulled":false,"numSkaters":0,"powerPlay":false},"away":{"team":{"id":22,"name":"Edmonton Oilers","link":"/api/v1/teams/22","abbreviation":"EDM","triCode":"EDM"},"goals":0,"shotsOnGoal":0,"goaliePulled":false,"numSkaters":0,"powerPlay":false}},"powerPlayStrength":"Even","hasShootout":false,"intermissionInfo":{"intermissionTimeRemaining":0,"intermissionTimeElapsed":0,"inIntermission":false}},"boxscore":{"teams":{"away":{"team":{"id":22,"name":"Edmonton Oilers","link":"/api/v1/teams/22","abbreviation":"EDM","triCode":"EDM"},"teamStats":{"teamSkaterStats":{"goals":0,"pim":0,"shots":0,"powerPlayPercentage":"0.0","powerPlayGoals":0,"powerPlayOpportunities":0,"faceOffWinPercentage":"0.0","blocked":0,"takeaways":0,"giveaways":0,"hits":0}},"players":{},"goalies":[],"skaters":[],"onIce":[],"onIcePlus":[],"scratches":[],"penaltyBox":[],"coaches":[]},"home":{"team":{"id":7,"name":"Buffalo Sabres","link":"/api/v1/teams/7","abbreviation":"BUF","triCode":"BUF"},"teamStats":{"teamSkaterStats":{"goals":0,"pim":0,"shots":0,"powerPlayPercentage":"0.0","powerPlayGoals":0,"powerPlayOpportunities":0,"faceOffWinPercentage":"0.0","blocked":0,"takeaways":0,"giveaways":0,"hits":0}},"players":{},"goalies":[],"skaters":[],"onIce":[],"onIcePlus":[],"scratches":[],"penaltyBox":[],"coaches":[]}},"officials":[]},"decisions":{}}}